conda_hooks/__init__.py
conda_hooks/env_store.py
conda_hooks/environment.py
conda_hooks/errors.py
conda_hooks/util.py
conda_hooks-0.5.0.dist-info/entry_points.txt
conda_hooks-0.5.0.dist-info/LICENSE
conda_hooks-0.5.0.dist-info/WHEEL
conda_hooks-0.5.0.dist-info/METADATA
conda_hooks-0.5.0.dist-info/RECORD
