Metadata-Version: 2.1
Name: conda-hooks
Version: 0.5.0
Summary: Keep anaconda environment files up to date
Home-page: https://github.com/f-koehler/conda-hooks
License: MIT
Author: Fabian Köhler
Author-email: fabian.koehler@protonmail.ch
Requires-Python: >=3.7,<4.0
Classifier: License :: OSI Approved :: MIT License
Classifier: Programming Language :: Python :: 3
Classifier: Programming Language :: Python :: 3.10
Classifier: Programming Language :: Python :: 3.7
Classifier: Programming Language :: Python :: 3.8
Classifier: Programming Language :: Python :: 3.9
Requires-Dist: PyYAML (>=5.3.1,<7.0.0)
Project-URL: Repository, https://github.com/f-koehler/conda-hooks
